getpybs.py
getpybs-0.1.0.dist-info/METADATA
getpybs-0.1.0.dist-info/WHEEL
getpybs-0.1.0.dist-info/entry_points.txt
getpybs-0.1.0.dist-info/licenses/LICENSE
getpybs-0.1.0.dist-info/RECORD
