Metadata-Version: 2.4
Name: getpybs
Version: 0.1.0
Summary: Fetch python-build-standalone binaries easily
Project-URL: Homepage, https://github.com/mliezun/getpybs
Project-URL: Repository, https://github.com/mliezun/getpybs
Project-URL: Issues, https://github.com/mliezun/getpybs/issues
Author-email: Miguel Liezun <liezun.js@gmail.com>
License: MIT
License-File: LICENSE
Keywords: binary,build,cpython,download,python,standalone
Classifier: Development Status :: 4 - Beta
Classifier: Intended Audience :: Developers
Classifier: License :: OSI Approved :: MIT License
Classifier: Operating System :: OS Independent
Classifier: Programming Language :: Python :: 3
Classifier: Programming Language :: Python :: 3.10
Classifier: Programming Language :: Python :: 3.11
Classifier: Programming Language :: Python :: 3.12
Classifier: Programming Language :: Python :: 3.13
Classifier: Topic :: Software Development :: Build Tools
Classifier: Topic :: System :: Software Distribution
Requires-Python: >=3.10
